pypi_simple_cli/__init__.py
pypi_simple_cli/__main__.py
pypi_simple_cli-0.1.6.dist-info/LICENSE
pypi_simple_cli-0.1.6.dist-info/METADATA
pypi_simple_cli-0.1.6.dist-info/WHEEL
pypi_simple_cli-0.1.6.dist-info/entry_points.txt
pypi_simple_cli-0.1.6.dist-info/top_level.txt
pypi_simple_cli-0.1.6.dist-info/RECORD
